email_profile/__init__.py
email_profile/cli.py
email_profile/core.py
email_profile/data.py
email_profile/message.py
email_profile/status.py
email_profile/utils.py
email_profile/where.py
email_profile/abstract/__init__.py
email_profile/abstract/controller.py
email_profile/abstract/model.py
email_profile/models/__init__.py
email_profile/models/attachment.py
email_profile/models/email.py
email_profile/models/mailbox.py
email_profile/serializers/__init__.py
email_profile/serializers/where.py
email_profile-0.4.0.dist-info/METADATA
email_profile-0.4.0.dist-info/WHEEL
email_profile-0.4.0.dist-info/licenses/LICENSE
email_profile-0.4.0.dist-info/RECORD
