Metadata-Version: 2.3
Name: email-profile
Version: 0.4.0
Summary: 📩 Email Profile
Project-URL: Homepage, https://github.com/linux-profile/email-profile
Project-URL: Issues, https://github.com/linux-profile/email-profile/issues
Project-URL: Repository, https://github.com/linux-profile/email-profile
Project-URL: Documentation, https://github.com/linux-profile/email-profile/blob/master/README.md
Author-email: Fernando Celmer <email@fernandocelmer.com>
License: MIT License
License-File: LICENSE
Classifier: Development Status :: 4 - Beta
Classifier: Intended Audience :: Developers
Classifier: License :: OSI Approved :: MIT License
Classifier: Natural Language :: English
Classifier: Operating System :: OS Independent
Classifier: Programming Language :: Python :: 3.8
Classifier: Programming Language :: Python :: 3.9
Classifier: Programming Language :: Python :: 3.10
Classifier: Programming Language :: Python :: 3.11
Classifier: Programming Language :: Python :: 3.12
Requires-Python: >=3.8
